tamr_toolbox/__init__.py
tamr_toolbox/data_io/__init__.py
tamr_toolbox/data_io/common.py
tamr_toolbox/data_io/csv.py
tamr_toolbox/data_io/dataframe.py
tamr_toolbox/data_io/file_system_type.py
tamr_toolbox/data_io/df_connect/__init__.py
tamr_toolbox/data_io/df_connect/client.py
tamr_toolbox/data_io/df_connect/jdbc_info.py
tamr_toolbox/dataset/__init__.py
tamr_toolbox/dataset/_dataset.py
tamr_toolbox/dataset/manage.py
tamr_toolbox/enrichment/__init__.py
tamr_toolbox/enrichment/address_mapping.py
tamr_toolbox/enrichment/address_validation.py
tamr_toolbox/enrichment/dictionary.py
tamr_toolbox/enrichment/enrichment_utils.py
tamr_toolbox/enrichment/translate.py
tamr_toolbox/enrichment/api_client/__init__.py
tamr_toolbox/enrichment/api_client/google_address_validate.py
tamr_toolbox/enrichment/api_client/google_translate.py
tamr_toolbox/filesystem/__init__.py
tamr_toolbox/filesystem/bash.py
tamr_toolbox/filesystem/cloud.py
tamr_toolbox/models/__init__.py
tamr_toolbox/models/attribute_type.py
tamr_toolbox/models/data_type.py
tamr_toolbox/models/operation_state.py
tamr_toolbox/models/project_artifacts.py
tamr_toolbox/models/project_steps.py
tamr_toolbox/models/project_type.py
tamr_toolbox/models/validation_check.py
tamr_toolbox/notifications/__init__.py
tamr_toolbox/notifications/common.py
tamr_toolbox/notifications/emails.py
tamr_toolbox/notifications/slack.py
tamr_toolbox/project/__init__.py
tamr_toolbox/project/_common/__init__.py
tamr_toolbox/project/_common/attribute_configuration.py
tamr_toolbox/project/_common/movement.py
tamr_toolbox/project/_common/schema.py
tamr_toolbox/project/_common/transformations.py
tamr_toolbox/project/categorization/__init__.py
tamr_toolbox/project/categorization/jobs.py
tamr_toolbox/project/categorization/metrics.py
tamr_toolbox/project/categorization/taxonomy.py
tamr_toolbox/project/golden_records/__init__.py
tamr_toolbox/project/golden_records/jobs.py
tamr_toolbox/project/mastering/__init__.py
tamr_toolbox/project/mastering/jobs.py
tamr_toolbox-1.11.1.dist-info/LICENSE
tamr_toolbox-1.11.1.dist-info/METADATA
tamr_toolbox-1.11.1.dist-info/WHEEL
tamr_toolbox-1.11.1.dist-info/top_level.txt
tamr_toolbox-1.11.1.dist-info/RECORD
