Metadata-Version: 2.1
Name: tamr-toolbox
Version: 1.11.1
Summary: Tools for Tamr
Home-page: https://github.com/Datatamer/tamr-toolbox
Author: Tamr Inc.
Author-email: 
Requires-Python: >=3.6
License-File: LICENSE
Requires-Dist: dataclasses-json (==0.5.6)
Requires-Dist: networkx (>=2.5)
Requires-Dist: PyYAML (==6.0)
Requires-Dist: requests (>=2.22)
Requires-Dist: tamr-unify-client (>=1.7.0)
Requires-Dist: packaging (>=21.3)
Provides-Extra: address-validation
Requires-Dist: googlemaps (==4.10.0) ; extra == 'address-validation'
Provides-Extra: all
Requires-Dist: pandas (>=0.21.0) ; extra == 'all'
Requires-Dist: aiohttp (==3.7.4.post0) ; extra == 'all'
Requires-Dist: slackclient (==2.7.2) ; extra == 'all'
Requires-Dist: responses (==0.10.14) ; extra == 'all'
Requires-Dist: paramiko (>=2.8.0) ; extra == 'all'
Requires-Dist: google-cloud-translate (==3.7.4) ; extra == 'all'
Requires-Dist: google-cloud-storage (>=2.0.0) ; extra == 'all'
Requires-Dist: boto3 (>=1.21.21) ; extra == 'all'
Requires-Dist: boto3-stubs-lite[essential] (>=1.21.21) ; extra == 'all'
Provides-Extra: gcs
Requires-Dist: google-cloud-storage (>=2.0.0) ; extra == 'gcs'
Provides-Extra: pandas
Requires-Dist: pandas (>=0.21.0) ; extra == 'pandas'
Provides-Extra: s3
Requires-Dist: boto3 (>=1.21.21) ; extra == 's3'
Requires-Dist: boto3-stubs-lite[essential] (>=1.21.21) ; extra == 's3'
Provides-Extra: slack
Requires-Dist: aiohttp (==3.7.4.post0) ; extra == 'slack'
Requires-Dist: slackclient (==2.7.2) ; extra == 'slack'
Provides-Extra: ssh
Requires-Dist: paramiko (>=2.8.0) ; extra == 'ssh'
Provides-Extra: testing
Requires-Dist: responses (==0.10.14) ; extra == 'testing'
Provides-Extra: translation
Requires-Dist: google-cloud-translate (==3.7.4) ; extra == 'translation'
